smartcrop/__init__.py
smartcrop/cli.py
smartcrop/library.py
smartcrop-0.4.1.dist-info/AUTHORS.md
smartcrop-0.4.1.dist-info/LICENSE
smartcrop-0.4.1.dist-info/METADATA
smartcrop-0.4.1.dist-info/WHEEL
smartcrop-0.4.1.dist-info/entry_points.txt
smartcrop-0.4.1.dist-info/top_level.txt
smartcrop-0.4.1.dist-info/RECORD
