Metadata-Version: 2.1
Name: smartcrop
Version: 0.4.1
Summary: smartcrop implementation in Python
Author-email: David Fischer <david@fisch3r.net>, Hideo Hattori <hhatto.jp@gmail.com>
Project-URL: homepage, https://github.com/smartcrop/smartcrop.py
Project-URL: documentation, https://github.com/smartcrop/smartcrop.py
Project-URL: repository, https://github.com/smartcrop/smartcrop.py
Keywords: image,crop,PIL,Pillow
Classifier: Development Status :: 3 - Alpha
Classifier: License :: OSI Approved :: MIT License
Classifier: Intended Audience :: Developers
Classifier: Operating System :: OS Independent
Classifier: Programming Language :: Python
Classifier: Programming Language :: Python :: 3
Classifier: Topic :: Utilities
Requires-Python: >=3.9
License-File: LICENSE
License-File: AUTHORS.md
Requires-Dist: numpy
Requires-Dist: pillow>=6.0.0
Provides-Extra: test
Requires-Dist: coverage<8,>=7.2.7; extra == "test"
Requires-Dist: flake8<7,>=6; extra == "test"
Requires-Dist: pylint<3,>=2.17.4; extra == "test"
Requires-Dist: pytest<8,>=7.3.1; extra == "test"
Requires-Dist: pytest-cov<5,>=4.1.0; extra == "test"
Requires-Dist: pytest-pylint<1,>=0.19.0; extra == "test"
Requires-Dist: types-Pillow; extra == "test"
Requires-Dist: types-Pygments; extra == "test"
Requires-Dist: types-colorama; extra == "test"
Requires-Dist: types-setuptools; extra == "test"
